{"mean cosine similarity transformed vectors": {"layer_0": "0.091013424", "layer_1": "0.06560988", "layer_2": "0.0610927", "layer_3": "0.084900044", "layer_4": "0.090013824", "layer_5": "0.075512886", "layer_6": "0.10062271", "layer_7": "0.15067706", "layer_8": "0.1860834", "layer_9": "0.2727208", "layer_10": "0.3987626", "layer_11": "0.6523335"}, "mean cosine similarity embeddings": {"layer_0": "0.17564738", "layer_1": "0.42446858", "layer_2": "0.59866685", "layer_3": "0.6483123", "layer_4": "0.6512574", "layer_5": "0.66007644", "layer_6": "0.6989611", "layer_7": "0.7357057", "layer_8": "0.7180019", "layer_9": "0.73461974", "layer_10": "0.8271714", "layer_11": "0.87868446", "layer_12": "0.9582621"}}